[
null,
{"id":1,"battlerName":"","characterIndex":0,"characterName":"","classId":2,"equips":[0,0,0,0,0],"faceIndex":1,"faceName":"","traits":[{"code":31,"dataId":4,"value":1},{"code":11,"dataId":1,"value":0.15},{"code":11,"dataId":2,"value":0.15},{"code":11,"dataId":3,"value":0.15},{"code":11,"dataId":4,"value":0.15},{"code":11,"dataId":5,"value":0.25},{"code":31,"dataId":15,"value":1},{"code":11,"dataId":7,"value":0.15},{"code":11,"dataId":8,"value":0.15},{"code":11,"dataId":9,"value":0.15},{"code":11,"dataId":10,"value":0.15},{"code":11,"dataId":11,"value":0.15},{"code":11,"dataId":12,"value":0.15},{"code":11,"dataId":13,"value":0.15},{"code":11,"dataId":14,"value":0.15},{"code":11,"dataId":15,"value":0.15}],"initialLevel":1,"maxLevel":99,"name":"Select","nickname":"","note":"","profile":""},
{"id":2,"battlerName":"AgumonX[8,6,1,0,false]","characterIndex":0,"characterName":"AgumonX%(8)","classId":2,"equips":[0,0,0,0,0],"faceIndex":0,"faceName":"Agumon X Line","traits":[{"code":31,"dataId":1,"value":1},{"code":11,"dataId":1,"value":0.15},{"code":11,"dataId":2,"value":0.25},{"code":11,"dataId":3,"value":0.05},{"code":11,"dataId":4,"value":0.15},{"code":11,"dataId":5,"value":0.25},{"code":31,"dataId":7,"value":1},{"code":11,"dataId":7,"value":0.15},{"code":11,"dataId":8,"value":0.25},{"code":11,"dataId":9,"value":0.05},{"code":11,"dataId":10,"value":0.15},{"code":11,"dataId":11,"value":0.15},{"code":11,"dataId":12,"value":0.15},{"code":11,"dataId":13,"value":0.15},{"code":11,"dataId":14,"value":0.15},{"code":11,"dataId":15,"value":0.15}],"initialLevel":1,"maxLevel":99,"name":"Agumon X","nickname":"","note":"<RestoreAfterLevelUpHPPercent: 100>\n<RestoreAfterLevelUpMPPercent: 100>","profile":""},
{"id":3,"battlerName":"Gaomon[8,6,1,0,false]","characterIndex":0,"characterName":"Gaomon%(8)","classId":3,"equips":[0,0,0,0,0],"faceIndex":0,"faceName":"Gaomon Line","traits":[{"code":31,"dataId":2,"value":1},{"code":11,"dataId":1,"value":0.05},{"code":11,"dataId":2,"value":0.15},{"code":11,"dataId":3,"value":0.25},{"code":11,"dataId":4,"value":0.05},{"code":11,"dataId":5,"value":0.25},{"code":31,"dataId":12,"value":1},{"code":11,"dataId":7,"value":0.15},{"code":11,"dataId":8,"value":0.15},{"code":11,"dataId":9,"value":0.15},{"code":11,"dataId":10,"value":0.05},{"code":11,"dataId":11,"value":0.25},{"code":11,"dataId":12,"value":0.15},{"code":11,"dataId":13,"value":0.15},{"code":11,"dataId":14,"value":0.15},{"code":11,"dataId":15,"value":0.15}],"initialLevel":1,"maxLevel":99,"name":"Gaomon","nickname":"","note":"<RestoreAfterLevelUpHPPercent: 100>\n<RestoreAfterLevelUpMPPercent: 100>","profile":""},
{"id":4,"battlerName":"Lalamon[8,6,1,0,false]","characterIndex":0,"characterName":"Lalamon%(8)","classId":4,"equips":[0,0,0,0,0],"faceIndex":0,"faceName":"Lalamon Line","traits":[{"code":31,"dataId":2,"value":1},{"code":11,"dataId":1,"value":0.05},{"code":11,"dataId":2,"value":0.15},{"code":11,"dataId":3,"value":0.25},{"code":11,"dataId":4,"value":0.05},{"code":11,"dataId":5,"value":0.25},{"code":31,"dataId":9,"value":1},{"code":11,"dataId":7,"value":0.25},{"code":11,"dataId":8,"value":0.15},{"code":11,"dataId":9,"value":0.15},{"code":11,"dataId":10,"value":0.15},{"code":11,"dataId":11,"value":0.05},{"code":11,"dataId":12,"value":0.15},{"code":11,"dataId":13,"value":0.15},{"code":11,"dataId":14,"value":0.15},{"code":11,"dataId":15,"value":0.15}],"initialLevel":1,"maxLevel":99,"name":"Lalamon","nickname":"","note":"<RestoreAfterLevelUpHPPercent: 100>\n<RestoreAfterLevelUpMPPercent: 100>","profile":""},
{"id":5,"battlerName":"Falcomon[8,6,1,0,false]","characterIndex":0,"characterName":"Falcomon%(8)","classId":5,"equips":[0,0,0,0,0],"faceIndex":0,"faceName":"Falcomon Line","traits":[{"code":31,"dataId":1,"value":1},{"code":11,"dataId":1,"value":0.15},{"code":11,"dataId":2,"value":0.25},{"code":11,"dataId":3,"value":0.05},{"code":11,"dataId":4,"value":0.05},{"code":11,"dataId":5,"value":0.25},{"code":31,"dataId":12,"value":1},{"code":11,"dataId":7,"value":0.15},{"code":11,"dataId":8,"value":0.15},{"code":11,"dataId":9,"value":0.15},{"code":11,"dataId":10,"value":0.05},{"code":11,"dataId":11,"value":0.25},{"code":11,"dataId":12,"value":0.15},{"code":11,"dataId":13,"value":0.15},{"code":11,"dataId":14,"value":0.15},{"code":11,"dataId":15,"value":0.15}],"initialLevel":1,"maxLevel":99,"name":"Falcomon","nickname":"","note":"<RestoreAfterLevelUpHPPercent: 100>\n<RestoreAfterLevelUpMPPercent: 100>","profile":""},
{"id":6,"battlerName":"Elecmon[8,6,1,0,false]","characterIndex":0,"characterName":"Elecmon%(8)","classId":6,"equips":[0,0,0,0,0],"faceIndex":0,"faceName":"Elecmon Line","traits":[{"code":31,"dataId":2,"value":1},{"code":11,"dataId":1,"value":0.05},{"code":11,"dataId":2,"value":0.15},{"code":11,"dataId":3,"value":0.25},{"code":11,"dataId":4,"value":0.05},{"code":11,"dataId":5,"value":0.25},{"code":31,"dataId":10,"value":1},{"code":11,"dataId":7,"value":0.15},{"code":11,"dataId":8,"value":0.05},{"code":11,"dataId":9,"value":0.15},{"code":11,"dataId":10,"value":0.25},{"code":11,"dataId":11,"value":0.15},{"code":11,"dataId":12,"value":0.15},{"code":11,"dataId":13,"value":0.15},{"code":11,"dataId":14,"value":0.15},{"code":11,"dataId":15,"value":0.15}],"initialLevel":1,"maxLevel":99,"name":"Elecmon","nickname":"","note":"<RestoreAfterLevelUpHPPercent: 100>\n<RestoreAfterLevelUpMPPercent: 100>","profile":""},
{"id":7,"battlerName":"FanBeemon[4,6,1,0,false]","characterIndex":0,"characterName":"FanBeemon%(4)","classId":7,"equips":[0,0,0,0,0],"faceIndex":0,"faceName":"FanBeemon Line","traits":[{"code":31,"dataId":3,"value":1},{"code":11,"dataId":1,"value":0.25},{"code":11,"dataId":2,"value":0.05},{"code":11,"dataId":3,"value":0.15},{"code":11,"dataId":4,"value":0.05},{"code":11,"dataId":5,"value":0.25},{"code":31,"dataId":10,"value":1},{"code":11,"dataId":7,"value":0.15},{"code":11,"dataId":8,"value":0.05},{"code":11,"dataId":9,"value":0.15},{"code":11,"dataId":10,"value":0.15},{"code":11,"dataId":11,"value":0.15},{"code":11,"dataId":12,"value":0.25},{"code":11,"dataId":13,"value":0.15},{"code":11,"dataId":14,"value":0.15},{"code":11,"dataId":15,"value":0.15}],"initialLevel":1,"maxLevel":99,"name":"FanBeemon","nickname":"","note":"<RestoreAfterLevelUpHPPercent: 100>\n<RestoreAfterLevelUpMPPercent: 100>","profile":""},
{"id":8,"battlerName":"Guilmon[8,6,1,0,false]","characterIndex":0,"characterName":"Guilmon%(8)","classId":8,"equips":[0,0,0,0,0],"faceIndex":0,"faceName":"Guilmon Line","traits":[{"code":31,"dataId":3,"value":1},{"code":11,"dataId":1,"value":0.25},{"code":11,"dataId":2,"value":0.05},{"code":11,"dataId":3,"value":0.15},{"code":11,"dataId":4,"value":0.05},{"code":11,"dataId":5,"value":0.25},{"code":31,"dataId":7,"value":1},{"code":11,"dataId":7,"value":0.15},{"code":11,"dataId":8,"value":0.25},{"code":11,"dataId":9,"value":0.05},{"code":11,"dataId":10,"value":0.15},{"code":11,"dataId":11,"value":0.15},{"code":11,"dataId":12,"value":0.15},{"code":11,"dataId":13,"value":0.15},{"code":11,"dataId":14,"value":0.15},{"code":11,"dataId":15,"value":0.15}],"initialLevel":1,"maxLevel":99,"name":"Guilmon","nickname":"","note":"<RestoreAfterLevelUpHPPercent: 100>\n<RestoreAfterLevelUpMPPercent: 100>","profile":""},
{"id":9,"battlerName":"Renamon[8,6,1,0,false]","characterIndex":0,"characterName":"Renamon%(8)","classId":9,"equips":[0,0,0,0,0],"faceIndex":0,"faceName":"Renamon Line","traits":[{"code":31,"dataId":2,"value":1},{"code":11,"dataId":1,"value":0.05},{"code":11,"dataId":2,"value":0.15},{"code":11,"dataId":3,"value":0.25},{"code":11,"dataId":4,"value":0.05},{"code":11,"dataId":5,"value":0.25},{"code":31,"dataId":9,"value":1},{"code":11,"dataId":7,"value":0.25},{"code":11,"dataId":8,"value":0.15},{"code":11,"dataId":9,"value":0.15},{"code":11,"dataId":10,"value":0.15},{"code":11,"dataId":11,"value":0.05},{"code":11,"dataId":12,"value":0.15},{"code":11,"dataId":13,"value":0.15},{"code":11,"dataId":14,"value":0.15},{"code":11,"dataId":15,"value":0.15}],"initialLevel":1,"maxLevel":99,"name":"Renamon","nickname":"","note":"<RestoreAfterLevelUpHPPercent: 100>\n<RestoreAfterLevelUpMPPercent: 100>","profile":""},
{"id":10,"battlerName":"Terriermon[8,6,1,0,false]","characterIndex":0,"characterName":"Terriermon%(8)","classId":10,"equips":[0,0,0,0,0],"faceIndex":0,"faceName":"Terriermon Line","traits":[{"code":31,"dataId":1,"value":1},{"code":11,"dataId":1,"value":0.15},{"code":11,"dataId":2,"value":0.25},{"code":11,"dataId":3,"value":0.05},{"code":11,"dataId":4,"value":0.05},{"code":11,"dataId":5,"value":0.25},{"code":31,"dataId":12,"value":1},{"code":11,"dataId":7,"value":0.15},{"code":11,"dataId":8,"value":0.15},{"code":11,"dataId":9,"value":0.15},{"code":11,"dataId":10,"value":0.05},{"code":11,"dataId":11,"value":0.25},{"code":11,"dataId":12,"value":0.15},{"code":11,"dataId":13,"value":0.15},{"code":11,"dataId":14,"value":0.15},{"code":11,"dataId":15,"value":0.15}],"initialLevel":1,"maxLevel":99,"name":"Terriermon","nickname":"","note":"<RestoreAfterLevelUpHPPercent: 100>\n<RestoreAfterLevelUpMPPercent: 100>","profile":""},
{"id":11,"battlerName":"AgumonC[8,6,1,0,false]","characterIndex":0,"characterName":"AgumonC%(8)","classId":11,"equips":[0,0,0,0,0],"faceIndex":0,"faceName":"AgumonC Line","traits":[{"code":31,"dataId":1,"value":1},{"code":11,"dataId":1,"value":0.15},{"code":11,"dataId":2,"value":0.25},{"code":11,"dataId":3,"value":0.05},{"code":11,"dataId":4,"value":0.05},{"code":11,"dataId":5,"value":0.25},{"code":31,"dataId":7,"value":1},{"code":11,"dataId":7,"value":0.15},{"code":11,"dataId":8,"value":0.25},{"code":11,"dataId":9,"value":0.05},{"code":11,"dataId":10,"value":0.15},{"code":11,"dataId":11,"value":0.15},{"code":11,"dataId":12,"value":0.15},{"code":11,"dataId":13,"value":0.15},{"code":11,"dataId":14,"value":0.15},{"code":11,"dataId":15,"value":0.15}],"initialLevel":1,"maxLevel":99,"name":"Agumon (Classic)","nickname":"","note":"<RestoreAfterLevelUpHPPercent: 100>\n<RestoreAfterLevelUpMPPercent: 100>","profile":""},
{"id":12,"battlerName":"Gabumon[8,6,1,0,false]","characterIndex":0,"characterName":"Gabumon%(8)","classId":12,"equips":[0,0,0,0,0],"faceIndex":0,"faceName":"Gabumon Line","traits":[{"code":31,"dataId":2,"value":1},{"code":11,"dataId":1,"value":0.05},{"code":11,"dataId":2,"value":0.15},{"code":11,"dataId":3,"value":0.25},{"code":11,"dataId":4,"value":0.05},{"code":11,"dataId":5,"value":0.25},{"code":31,"dataId":7,"value":1},{"code":11,"dataId":7,"value":0.15},{"code":11,"dataId":8,"value":0.25},{"code":11,"dataId":9,"value":0.05},{"code":11,"dataId":10,"value":0.15},{"code":11,"dataId":11,"value":0.15},{"code":11,"dataId":12,"value":0.15},{"code":11,"dataId":13,"value":0.15},{"code":11,"dataId":14,"value":0.15},{"code":11,"dataId":15,"value":0.15}],"initialLevel":1,"maxLevel":99,"name":"Gabumon","nickname":"","note":"<RestoreAfterLevelUpHPPercent: 100>\n<RestoreAfterLevelUpMPPercent: 100>","profile":""},
{"id":13,"battlerName":"Gomamon[8,6,1,0,false]","characterIndex":0,"characterName":"Gomamon%(8)","classId":13,"equips":[0,0,0,0,0],"faceIndex":0,"faceName":"Gomamon Line","traits":[{"code":31,"dataId":2,"value":1},{"code":11,"dataId":1,"value":0.05},{"code":11,"dataId":2,"value":0.15},{"code":11,"dataId":3,"value":0.25},{"code":11,"dataId":4,"value":0.05},{"code":11,"dataId":5,"value":0.25},{"code":31,"dataId":8,"value":1},{"code":11,"dataId":7,"value":0.05},{"code":11,"dataId":8,"value":0.15},{"code":11,"dataId":9,"value":0.15},{"code":11,"dataId":10,"value":0.25},{"code":11,"dataId":11,"value":0.15},{"code":11,"dataId":12,"value":0.15},{"code":11,"dataId":13,"value":0.15},{"code":11,"dataId":14,"value":0.15},{"code":11,"dataId":15,"value":0.15}],"initialLevel":1,"maxLevel":99,"name":"Gomamon","nickname":"","note":"<RestoreAfterLevelUpHPPercent: 100>\n<RestoreAfterLevelUpMPPercent: 100>","profile":""},
{"id":14,"battlerName":"Tentomon[8,6,1,0,false]","characterIndex":0,"characterName":"Tentomon%(8)","classId":14,"equips":[0,0,0,0,0],"faceIndex":0,"faceName":"Tentomon Line","traits":[{"code":31,"dataId":1,"value":1},{"code":11,"dataId":1,"value":0.15},{"code":11,"dataId":2,"value":0.25},{"code":11,"dataId":3,"value":0.05},{"code":11,"dataId":4,"value":0.05},{"code":11,"dataId":5,"value":0.25},{"code":31,"dataId":10,"value":1},{"code":11,"dataId":7,"value":0.15},{"code":11,"dataId":8,"value":0.05},{"code":11,"dataId":9,"value":0.15},{"code":11,"dataId":10,"value":0.15},{"code":11,"dataId":11,"value":0.15},{"code":11,"dataId":12,"value":0.25},{"code":11,"dataId":13,"value":0.15},{"code":11,"dataId":14,"value":0.15},{"code":11,"dataId":15,"value":0.15}],"initialLevel":1,"maxLevel":99,"name":"Tentomon","nickname":"","note":"<RestoreAfterLevelUpHPPercent: 100>\n<RestoreAfterLevelUpMPPercent: 100>","profile":""},
{"id":15,"battlerName":"Patamon[8,6,1,0,false]","characterIndex":0,"characterName":"Patamon%(8)","classId":15,"equips":[0,0,0,0,0],"faceIndex":0,"faceName":"Patamon Line","traits":[{"code":31,"dataId":1,"value":1},{"code":11,"dataId":1,"value":0.15},{"code":11,"dataId":2,"value":0.25},{"code":11,"dataId":3,"value":0.05},{"code":11,"dataId":4,"value":0.05},{"code":11,"dataId":5,"value":0.25},{"code":31,"dataId":12,"value":1},{"code":11,"dataId":7,"value":0.15},{"code":11,"dataId":8,"value":0.15},{"code":11,"dataId":9,"value":0.15},{"code":11,"dataId":10,"value":0.05},{"code":11,"dataId":11,"value":0.25},{"code":11,"dataId":12,"value":0.15},{"code":11,"dataId":13,"value":0.15},{"code":11,"dataId":14,"value":0.15},{"code":11,"dataId":15,"value":0.15}],"initialLevel":1,"maxLevel":99,"name":"Patamon","nickname":"","note":"<RestoreAfterLevelUpHPPercent: 100>\n<RestoreAfterLevelUpMPPercent: 100>","profile":""},
{"id":16,"battlerName":"Palmon[8,6,1,0,false]","characterIndex":0,"characterName":"Palmon%(8)","classId":16,"equips":[0,0,0,0,0],"faceIndex":0,"faceName":"Palmon Line","traits":[{"code":31,"dataId":2,"value":1},{"code":11,"dataId":1,"value":0.05},{"code":11,"dataId":2,"value":0.15},{"code":11,"dataId":3,"value":0.25},{"code":11,"dataId":4,"value":0.05},{"code":11,"dataId":5,"value":0.25},{"code":31,"dataId":9,"value":1},{"code":11,"dataId":7,"value":0.25},{"code":11,"dataId":8,"value":0.15},{"code":11,"dataId":9,"value":0.15},{"code":11,"dataId":10,"value":0.15},{"code":11,"dataId":11,"value":0.05},{"code":11,"dataId":12,"value":0.15},{"code":11,"dataId":13,"value":0.15},{"code":11,"dataId":14,"value":0.15},{"code":11,"dataId":15,"value":0.15}],"initialLevel":1,"maxLevel":99,"name":"Palmon (Togemon)","nickname":"","note":"<RestoreAfterLevelUpHPPercent: 100>\n<RestoreAfterLevelUpMPPercent: 100>","profile":""},
{"id":17,"battlerName":"Piyomon[8,6,1,0,false]","characterIndex":0,"characterName":"Piyomon%(8)","classId":17,"equips":[0,0,0,0,0],"faceIndex":0,"faceName":"Piyomon Line","traits":[{"code":31,"dataId":1,"value":1},{"code":11,"dataId":1,"value":0.15},{"code":11,"dataId":2,"value":0.25},{"code":11,"dataId":3,"value":0.05},{"code":11,"dataId":4,"value":0.05},{"code":11,"dataId":5,"value":0.25},{"code":31,"dataId":7,"value":1},{"code":11,"dataId":7,"value":0.15},{"code":11,"dataId":8,"value":0.15},{"code":11,"dataId":9,"value":0.15},{"code":11,"dataId":10,"value":0.05},{"code":11,"dataId":11,"value":0.25},{"code":11,"dataId":12,"value":0.15},{"code":11,"dataId":13,"value":0.15},{"code":11,"dataId":14,"value":0.15},{"code":11,"dataId":15,"value":0.15}],"initialLevel":1,"maxLevel":99,"name":"Piyomon","nickname":"","note":"<RestoreAfterLevelUpHPPercent: 100>\n<RestoreAfterLevelUpMPPercent: 100>","profile":""},
{"id":18,"battlerName":"Salamon[8,6,1,0,false]","characterIndex":0,"characterName":"Salamon%(8)","classId":18,"equips":[0,0,0,0,0],"faceIndex":0,"faceName":"Salamon LIne","traits":[{"code":31,"dataId":1,"value":1},{"code":11,"dataId":1,"value":0.15},{"code":11,"dataId":2,"value":0.25},{"code":11,"dataId":3,"value":0.05},{"code":11,"dataId":4,"value":0.05},{"code":11,"dataId":5,"value":0.25},{"code":31,"dataId":13,"value":1},{"code":11,"dataId":7,"value":0.15},{"code":11,"dataId":8,"value":0.15},{"code":11,"dataId":9,"value":0.15},{"code":11,"dataId":10,"value":0.15},{"code":11,"dataId":11,"value":0.15},{"code":11,"dataId":12,"value":0.15},{"code":11,"dataId":13,"value":0.15},{"code":11,"dataId":14,"value":0.25},{"code":11,"dataId":15,"value":0.15}],"initialLevel":1,"maxLevel":99,"name":"Salamon","nickname":"","note":"<RestoreAfterLevelUpHPPercent: 100>\n<RestoreAfterLevelUpMPPercent: 100>","profile":""}
]