[
null,
{"id":1,"animationId":1,"description":"Aumenta o AT do Digimon em 70 pontos.","etypeId":1,"traits":[{"code":31,"dataId":17,"value":1}],"iconIndex":118,"name":"AT Chipset Lv1","note":"<Suffixes>\n11 100%\n</Suffixes>","params":[0,0,70,0,0,0,0,0],"price":300,"wtypeId":1},
{"id":2,"animationId":1,"description":"Aumenta o AT do Digimon em 75 pontos.","etypeId":1,"traits":[{"code":31,"dataId":17,"value":1}],"iconIndex":118,"name":"AT Chipset Lv2","note":"<Suffixes>\n11 100%\n</Suffixes>","params":[0,0,75,0,0,0,0,0],"price":600,"wtypeId":1},
{"id":3,"animationId":1,"description":"Aumenta o AT do Digimon em 80 pontos.","etypeId":1,"traits":[{"code":31,"dataId":17,"value":1}],"iconIndex":118,"name":"AT Chipset Lv3","note":"<Suffixes>\n11 100%\n</Suffixes>","params":[0,0,80,0,0,0,0,0],"price":900,"wtypeId":1},
{"id":4,"animationId":1,"description":"Aumenta o AT do Digimon em 85 pontos.","etypeId":1,"traits":[{"code":31,"dataId":17,"value":1}],"iconIndex":118,"name":"AT Chipset Lv4","note":"<Suffixes>\n11 100%\n</Suffixes>\n<Synthesis Ingredients>\nitem 502: 2\nitem 503: 1\n</Synthesis Ingredients>\n<Mask Name: AT Chipset Lv4>","params":[0,0,85,0,0,0,0,0],"price":2200,"wtypeId":1},
{"id":5,"animationId":1,"description":"Aumenta o AT do Digimon em 90 pontos.","etypeId":1,"traits":[{"code":31,"dataId":17,"value":1}],"iconIndex":118,"name":"AT Chipset Lv5","note":"<Suffixes>\n11 100%\n</Suffixes>\n<Synthesis Ingredients>\nitem 502: 4\nitem 504: 1\n</Synthesis Ingredients>\n<Mask Name: AT Chipset Lv5>","params":[0,0,90,0,0,0,0,0],"price":2900,"wtypeId":1},
{"id":6,"animationId":1,"description":"Aumenta o AT do Digimon em 95 pontos.","etypeId":1,"traits":[{"code":31,"dataId":17,"value":1}],"iconIndex":118,"name":"AT Chipset Lv6","note":"<Suffixes>\n11 100%\n</Suffixes>\n<Synthesis Ingredients>\nitem 502: 8\nitem 505: 1\n</Synthesis Ingredients>\n<Mask Name: AT Chipset Lv6>","params":[0,0,95,0,0,0,0,0],"price":3700,"wtypeId":1},
{"id":7,"animationId":1,"description":"Aumenta o AT do Digimon em 100 pontos.","etypeId":1,"traits":[{"code":31,"dataId":17,"value":1}],"iconIndex":118,"name":"AT Chipset Lv7","note":"<Suffixes>\n11 100%\n</Suffixes>\n<Synthesis Ingredients>\nitem 502: 16\nitem 506: 1\n</Synthesis Ingredients>\n<Mask Name: AT Chipset Lv7>","params":[0,0,100,0,0,0,0,0],"price":4850,"wtypeId":1},
{"id":8,"animationId":1,"description":"Aumenta o AT do Digimon em 110 pontos.","etypeId":1,"traits":[{"code":31,"dataId":17,"value":1}],"iconIndex":118,"name":"AT Chipset Lv8","note":"<Suffixes>\n11 100%\n</Suffixes>\n<Synthesis Ingredients>\nitem 502: 32\nitem 507: 1\n</Synthesis Ingredients>\n<Mask Name: AT Chipset Lv8>","params":[0,0,110,0,0,0,0,0],"price":6720,"wtypeId":1},
{"id":9,"animationId":1,"description":"Aumenta o AT do Digimon em 130 pontos.","etypeId":1,"traits":[{"code":31,"dataId":17,"value":1}],"iconIndex":118,"name":"AT Chipset Lv9","note":"<Suffixes>\n11 100%\n</Suffixes>\n<Synthesis Ingredients>\nitem 502: 64\nitem 508: 1\n</Synthesis Ingredients>\n<Mask Name: AT Chipset Lv9>","params":[0,0,130,0,0,0,0,0],"price":7500,"wtypeId":1},
{"id":10,"animationId":1,"description":"Aumenta o AT do Digimon em 140 pontos.","etypeId":1,"traits":[{"code":31,"dataId":17,"value":1}],"iconIndex":118,"name":"AT Chipset Lv10","note":"<Suffixes>\n11 100%\n</Suffixes>","params":[0,0,140,0,0,0,0,0],"price":10000,"wtypeId":1},
{"id":11,"animationId":0,"description":"","etypeId":1,"traits":[{"code":22,"dataId":0,"value":0}],"iconIndex":0,"name":"","note":"<prefixSuffixParameters: ATK 0>","params":[0,0,0,0,0,0,0,0],"price":0,"wtypeId":0}
]